firewheel_repo_tutorials/acme/README.rst
firewheel_repo_tutorials/acme/run/MANIFEST
firewheel_repo_tutorials/acme/run/README.rst
firewheel_repo_tutorials/acme/set_hostname/MANIFEST
firewheel_repo_tutorials/acme/set_hostname/README.rst
firewheel_repo_tutorials/acme/set_hostname/plugin.py
firewheel_repo_tutorials/acme/set_hostname/set_hostname.py
firewheel_repo_tutorials/acme/topology/MANIFEST
firewheel_repo_tutorials/acme/topology/README.rst
firewheel_repo_tutorials/acme/topology/plugin.py
firewheel_repo_tutorials/bios/.gitignore
firewheel_repo_tutorials/bios/INSTALL
firewheel_repo_tutorials/bios/MANIFEST
firewheel_repo_tutorials/bios/README.rst
firewheel_repo_tutorials/bios/plugin.py
firewheel_repo_tutorials/bios/images/.gitkeep
firewheel_repo_tutorials/simple-server/MANIFEST
firewheel_repo_tutorials/simple-server/README.rst
firewheel_repo_tutorials/simple-server/model_component_objects.py
firewheel_repo_tutorials/simple-server/plugin.py
firewheel_repo_tutorials/simple-server/vm_resources/.gitkeep
firewheel_repo_tutorials-2.7.0.dist-info/LICENSE
firewheel_repo_tutorials-2.7.0.dist-info/METADATA
firewheel_repo_tutorials-2.7.0.dist-info/WHEEL
firewheel_repo_tutorials-2.7.0.dist-info/entry_points.txt
firewheel_repo_tutorials-2.7.0.dist-info/top_level.txt
firewheel_repo_tutorials-2.7.0.dist-info/RECORD
